Workbook

Sheet Panduan
A1: PANDUAN PENGGUNAAN — PROJECT RISK & HEALTH DASHBOARD v3
A2: Versi 3.0 | Dibuat untuk memudahkan pelaporan risiko dan kesehatan proyek secara berkala.
A4: 1. PENDAHULUAN
A5: Dashboard ini dirancang untuk memantau kesehatan proyek melalui 5 pilar utama:
A6: a. Financial Health (CPI) — efisiensi biaya
A7: b. Schedule Health (SPI) — efisiensi jadwal
A8: c. Supply Readiness Index (SRI) — kesiapan pasokan bahan baku
A9: d. Project Execution Index (PEI) — pelaksanaan proyek fisik
A10: e. Commercial Readiness Index (CRI) — kesiapan komersial
A12: 2. STRUKTUR FILE EXCEL
A13: Sheet | C13: Fungsi | F13: Siapa Mengisi
A14: Config | C14: Pengaturan global: nama proyek, bobot pilar, warna | F14: PM / PMO (sekali)
A15: Panduan | C15: Manual penggunaan (sheet ini) | F15: Hanya dibaca
A16: Referensi_Threshold | C16: Referensi formula, threshold, skala risiko | F16: Risk Manager (sekali)
A17: Input_Bulanan | C17: Input data utama setiap bulan | F17: Project Control (bulanan)
A18: Risk_Action_Tracker | C18: Tracker aksi mitigasi & keputusan Direksi | F18: Project Control (bulanan)
A19: Dashboard | C19: Ringkasan visual otomatis | F19: Otomatis
A21: 3. PANDUAN WARNA SEL
A22: KUNING (font biru) | B22: Isi data Anda di sini
A23: ABU-ABU | B23: Jangan diubah manual
A26: 4. MENAMBAH BARIS BARU — PANDUAN PER JENIS DATA
A27: PENTING: Setiap jenis data memerlukan tindakan di sheet yang berbeda. Baca panduan per jenis di bawah ini.
A29: 4A. MENAMBAH PARAMETER EWS BARU
A30: Input_Bulanan ✏️ | C30: HARUS DIUBAH
B31: → Buka seksi 8 (EWS) — cari baris terakhir data (saat ini baris 67–69).
B32: → Klik kanan di nomor baris terakhir → pilih 'Insert' → 'Entire Row'.
B33: → Isi kolom kuning: C=Nama Parameter, D=Deskripsi Target, E=Nilai Aktual, F=Nilai Threshold (Numerik), G=Buffer Waspada (Angka).
B34: → Salin formula kolom H (Status EWS) dari baris di atasnya ke baris baru.
B35: → Catatan: untuk indikator tanggal, gunakan formula IF(E<=F+G) ; untuk indikator %, gunakan IF(E>=F-G).
A36: Referensi_Threshold ✅ | C36: TIDAK PERLU DIUBAH
B37: → Sheet ini hanya berisi metodologi & panduan warna — tidak ada referensi langsung ke baris EWS.
A38: Risk_Action_Tracker ✅ | C38: TIDAK PERLU DIUBAH
B39: → Tidak ada hubungan langsung ke data EWS.
A40: HTML Dashboard ✅ | C40: OTOMATIS
B41: → Importer HTML membaca seluruh baris EWS secara dinamis. Import ulang Excel setelah menambah baris.
A43: 4B. MENAMBAH TOP RISK BARU
A44: Input_Bulanan ✏️ | C44: HARUS DIUBAH (PRIORITAS 1)
B45: → Buka seksi 9 (TOP RISK REGISTER) — cari baris terakhir data (saat ini baris 75–78).
B46: → Klik kanan di nomor baris terakhir → pilih 'Insert' → 'Entire Row'.
B47: → Isi kolom kuning: C=Kode (C5, C6, dst.), D=Deskripsi Risiko, E=Kategori, F=L (1-5), G=C (1-5).
B48: → WAJIB: Salin formula kolom H (Score/Skala) dan I (Risk Level) dari baris di atasnya. Formula ini pakai =INDEX(Referensi_Threshold!...) — jangan ditulis manual.
A49: Risk_Action_Tracker ✏️ | C49: HARUS DIUBAH (LANGKAH 2)
B50: → Buka seksi 'TOP RISK REGISTER' di Risk_Action_Tracker (saat ini baris 24–27).
B51: → Klik kanan di baris terakhir → 'Insert' → 'Entire Row'.
B52: → Salin formula =Input_Bulanan!C75, !D75, !E75, !F75, !G75 dari baris di atasnya, lalu sesuaikan nomor baris sumber (misal ganti 75 → 79 untuk baris baru).
A53: Referensi_Threshold ✅ | C53: TIDAK PERLU DIUBAH
B54: → Tabel skala risiko 5x5 sudah lengkap — formula di Input_Bulanan akan otomatis lookup.
A55: HTML Dashboard ✅ | C55: OTOMATIS
B56: → Importer HTML membaca seluruh baris Top Risk secara dinamis.
A58: 4C. MENAMBAH EXECUTIVE ACTION BARU
A59: Risk_Action_Tracker ✏️ | C59: HARUS DIUBAH (SATU-SATUNYA)
B60: → Buka tabel utama (baris 6–10) — satu baris = satu aksi eksekutif.
B61: → Klik kanan di baris terakhir data → 'Insert' → 'Entire Row'.
B62: → Isi kolom: B=No urut, C=Isu Strategis, D=Kategori & Level Risiko, E=Keputusan & Rencana Tindakan, F=PIC, G=Perkiraan Dampak.
B63: → KUNCI: Isi kolom H (Prioritas Dashboard) dengan angka 1, 2, 3… Angka 1 = paling prioritas. Kosongkan atau isi 0 = tidak tampil di slide utama.
A64: Input_Bulanan ✅ | C64: TIDAK PERLU DIUBAH
B65: → Input_Bulanan tidak punya hubungan langsung ke tabel Executive Actions.
A66: Referensi_Threshold ✅ | C66: TIDAK PERLU DIUBAH
B67: → Tidak ada referensi ke tabel Executive Actions.
A68: HTML Dashboard ✅ | C68: OTOMATIS
B69: → Importer membaca semua baris dari Risk_Action_Tracker dan menampilkan berdasarkan urutan Prioritas Dashboard.
A72: 4D. MENAMBAH PARAMETER SUB-INDEX (SRI / PEI / CRI)
A73: Referensi_Threshold ✏️ | C73: HARUS DIUBAH (LANGKAH 1)
B74: → Buka seksi 2 (SRI), 3 (PEI), atau 4 (CRI).
B75: → Klik kanan pada baris parameter terakhir sebelum TOTAL → 'Insert' → 'Entire Row'.
B76: → Isi kolom A (Nama Parameter), B (Bobot), C (Deskripsi).
B77: → PERINGATAN: Pastikan baris TOTAL BOBOT bernilai 1.00! Jika tidak 1.00, sel akan berubah menjadi MERAH.
A78: Input_Bulanan ✏️ | C78: HARUS DIUBAH (LANGKAH 2)
B79: → Buka seksi 2 (SRI), 3 (PEI), atau 4 (CRI) sesuai dengan yang diubah.
B80: → Klik kanan pada baris sebelum TOTAL → 'Insert' → 'Entire Row'.
B81: → Isi kolom C dengan Nama Parameter persis seperti di Referensi_Threshold.
B82: → Isi kolom D dengan Nilai Aktual (%) di area kuning.
B83: → Tautkan kolom E (Bobot) ke sheet Referensi_Threshold (contoh: =Referensi_Threshold!B24).
B84: → Salin formula kolom F (Nilai Tertimbang) dari baris di atasnya.
B85: → PERINGATAN: Pastikan kolom E baris TOTAL bernilai 1.00 (akan MERAH jika salah).
A88: 5. MENGUBAH BOBOT PILAR & SUB-INDEKS
A89: a. Bobot 5 Pilar PHS (Financial, Schedule, SRI, PEI, CRI) → ubah di sheet Config, Seksi B.
A90: b. Bobot Komponen Risk Index (Supply, Execution, Commercial) → ubah di sheet Config, Seksi C.
A91: c. Bobot parameter SRI, PEI, CRI → ikuti panduan 4D di atas.
A92: d. PASTIKAN total bobot setiap kelompok = 1.00 — sel total akan berwarna MERAH jika salah.
A93: e. Setelah simpan, import ulang Excel ke HTML — bobot baru otomatis diterapkan.
A95: 6. MENGUBAH THRESHOLD, KRITERIA RISIKO & BUFFER EWS
A96: a. Batas RAG (Hijau/Kuning/Oranye) per pilar → Config, Seksi F.
A97: b. Buffer Waspada EWS per parameter → Config, Seksi G.
A98: c. Kriteria Likelihood & Consequence → Config, Seksi H & I.
A99: d. Batas Skala Risiko per level → Config, Seksi J.
A101: 7. MENGATUR PRIORITAS EXECUTIVE ACTIONS DI DASHBOARD
... A109: c. Gunakan tombol PNG/JPG/PDF untuk mengekspor slide presentasi.

Sheet Config
A1: KONFIGURASI GLOBAL — PROJECT RISK & HEALTH DASHBOARD
A2: Sheet ini adalah pusat pengaturan. Ubah nilai di kolom B untuk menyesuaikan seluruh dashboard (Excel & HTML).
A4: A. IDENTITAS PROYEK
A5: Parameter | B5: Nilai | C5: Keterangan
A6: Nama Perusahaan | B6: PT Pupuk Kaltim | C6: Nama lengkap perusahaan pemilik proyek
A7: Nama Proyek | B7: Soda Ash | C7: Nama proyek yang dilaporkan
A8: Kapasitas Produksi | B8: 300.000 MTPY | C8: Kapasitas desain pabrik
A10: B. BOBOT 5 PILAR PROJECT HEALTH SCORE (PHS)
A11: Pilar Kesehatan | B11: Bobot | C11: Keterangan | D11: Justifikasi Bobot
A12: Financial Health | B12: 0.2 | C12: Berdasarkan CPI | D12: Mencerminkan standar AACE International; Cost Performance (CPI) adalah tolok ukur utama finansial.
A13: Schedule Health | B13: 0.2 | C13: Berdasarkan SPI | D13: Berdasarkan PMI PMBOK; Schedule Performance (SPI) memiliki bobot seimbang dengan biaya.
A14: Supply Readiness (SRI) | B14: 0.2 | C14: Indeks kesiapan pasokan bahan baku | D14: Praktik industri kimia (Soda Ash): jaminan bahan baku (garam) sangat krusial sebelum operasional.
A15: Project Execution (PEI) | B15: 0.2 | C15: Indeks pelaksanaan proyek fisik | D15: Penilaian kemajuan fisik (EPC) standar sesuai baseline S-Curve konstruksi.
A16: Commercial Readiness (CRI) | B16: 0.2 | C16: Indeks kesiapan komersial | D16: Kesiapan offtaker dan komersial diberi porsi seimbang untuk memastikan penyerapan produk.
A17: TOTAL BOBOT | B17: =SUM(B12:B16) -> 1 | C17: Harus = 1.00
A19: C. BOBOT OVERALL RISK INDEX
A20: Komponen Risiko | B20: Bobot | C20: Keterangan | D20: Justifikasi Bobot
A21: Supply Risk Index | B21: 0.4 | C21: Bahan baku, logistik | D21: Bahan baku (garam) merupakan penggerak utama produksi Soda Ash, risiko suplai berdampak tertinggi.
A22: Execution Risk Index | B22: 0.4 | C22: Engineering, procurement, construction | D22: Risiko keterlambatan EPC sangat kritikal terhadap NPV proyek (Capital Intensive).
A23: Commercial Risk Index | B23: 0.2 | C23: Offtake, marketing, distribusi | D23: Risiko komersial penting, namun dapat disesuaikan seiring ramp-up produksi.
A24: TOTAL BOBOT | B24: =SUM(B21:B23) -> 1
A26: D. PENGATURAN TAMPILAN DASHBOARD
A27: Parameter | B27: Nilai | C27: Keterangan
A28: Jumlah Tampilan Executive Actions | B28: 5 | C28: Batas maksimal action yang ditampilkan di dashboard sesuai urutan prioritas.
A29: [USANG] EWS Buffer (Pindah ke Input_Bulanan) | B29: - | C29: Pengaturan buffer EWS sekarang dilakukan per-item di sheet Input_Bulanan (Kolom G)
A31: E. KUSTOMISASI WARNA (HEX CODE)
A32: Elemen | B32: Hex Code | C32: Preview
A33: Warna Hijau (Aman) | B33: #2E9B57 | C33: Preview
A34: Warna Kuning (Pantau) | B34: #E8B93A | C34: Preview
A35: Warna Oranye (Waspada) | B35: #E4622E | C35: Preview
A36: Warna Merah (Kritis) | B36: #C0392B | C36: Preview
A37: Warna Navy (Aksen) | B37: #0B1F3A | C37: Preview
A39: F. BATAS TOLERANSI RAG (RED-AMBER-GREEN) — DAPAT DISESUAIKAN
A40: Angka di bawah adalah batas HIJAU (Aman). Sistem otomatis hitung Kuning = 95%, Oranye = 90% dari batas Hijau.
A41: Parameter | B41: Nilai Batas HIJAU (Aman) | C41: Keterangan
A42: CPI Batas Hijau | B42: 1 | C42: CPI >= nilai ini → Hijau / Aman
A43: CPI Batas Kuning | B43: 0.95 | C43: CPI >= nilai ini → Kuning (auto: =CPI Hijau × 0,95)
A44: CPI Batas Oranye | B44: 0.9 | C44: CPI >= nilai ini → Oranye (auto: =CPI Hijau × 0,90)
A45: SPI Batas Hijau | B45: 1 | C45: SPI >= nilai ini → Hijau / Aman
A46: SPI Batas Kuning | B46: 0.95 | C46: SPI >= nilai ini → Kuning (auto: =SPI Hijau × 0,95)
A47: SPI Batas Oranye | B47: 0.9 | C47: SPI >= nilai ini → Oranye (auto: =SPI Hijau × 0,90)
A48: SRI Batas Hijau (%) | B48: 90 | C48: SRI >= nilai ini → Hijau / Aman
A49: SRI Batas Kuning (%) | B49: 75 | C49: SRI >= nilai ini → Kuning / Perhatian
A50: SRI Batas Oranye (%) | B50: 65 | C50: SRI >= nilai ini → Oranye / Waspada
A51: PEI Batas Hijau (%) | B51: 90 | C51: Progres fisik >= nilai ini → Hijau
A52: PEI Batas Kuning (%) | B52: 80 | C52: Progres fisik >= nilai ini → Kuning
A53: PEI Batas Oranye (%) | B53: 70 | C53: Progres fisik >= nilai ini → Oranye
... A59: PHS Batas Oranye (%) | B59: 70 | C59: PHS >= nilai ini → Waspada
A62: G. [USANG] BUFFER WASPADA EWS - TIDAK DIGUNAKAN LAGI
A63: Seluruh pengaturan EWS kini dinamis dan dilakukan langsung di sheet Input_Bulanan.
A64: - | B64: - | C64: -
A65: - | B65: - | C65: -
A66: - | B66: - | C66: -
A67: - | B67: - | C67: -
A69: H. KRITERIA LIKELIHOOD (PROBABILITAS) — DAPAT DISESUAIKAN
A70: Ubah nama kategori dan batas probabilitas. Referensi_Threshold akan otomatis mengikuti.
A71: Level (L) | B71: Nama Kategori | C71: Batas Probabilitas (%) | D71: Keterangan Singkat
A72: 1 | B72: Sangat Jarang Terjadi | C72: < 10% | D72: Hampir tidak pernah terjadi selama siklus proyek
A73: 2 | B73: Jarang Terjadi | C73: 10 – 30% | D73: Pernah terjadi, namun jarang
A74: 3 | B74: Bisa Terjadi | C74: 30 – 50% | D74: Pernah terjadi beberapa kali
A75: 4 | B75: Sangat Mungkin Terjadi | C75: 50 – 70% | D75: Kondisi & indikasi sudah muncul
A76: 5 | B76: Hampir Pasti Terjadi | C76: > 70% | D76: Sudah terdapat indikasi kuat akan terjadi
A79: I. KRITERIA CONSEQUENCE (DAMPAK) — DAPAT DISESUAIKAN
A80: Ubah nama kategori dan kriteria dampak sesuai kebutuhan proyek. Referensi_Threshold otomatis mengikuti.
A81: Level (C) | B81: Nama Kategori | C81: Kriteria Deskriptif 1 | D81: Kriteria Deskriptif 2
A82: 1 | B82: Sangat Rendah | C82: Dampak biaya dapat diabaikan (< USD 0.5 Jt) | D82: Tidak ada keterlambatan signifikan (maks 1 bln)
A83: 2 | B83: Rendah | C83: Dampak biaya minor (USD 0.5 - 2 Jt) | D83: Keterlambatan minor (hingga 3 bln)
A84: 3 | B84: Moderat | C84: Dampak biaya moderat (USD 2 - 10 Jt) | D84: Keterlambatan berdampak pada jadwal utama (hingga 6 bln)
A85: 4 | B85: Tinggi | C85: Dampak biaya signifikan (USD 10 - 30 Jt) | D85: Keterlambatan penyelesaian proyek (hingga 12 bln)
A86: 5 | B86: Sangat Tinggi | C86: Dampak biaya krisis (> USD 30 Jt) | D86: Proyek terancam batal / sangat terlambat (> 24 bln)
A89: J. BATAS SKALA RISIKO (RISK RANKING) — DAPAT DISESUAIKAN
A90: Tentukan batas skala (skor L×C) untuk setiap level risiko. Risk Index (0-100) dihitung terpisah.
A91: Level Risiko | B91: Batas Bawah Skala | C91: Batas Atas Skala | D91: Overall Risk Index Range
A92: Low | B92: 1 | C92: 5 | D92: 0 – 20
A93: Low to Moderate | B93: 6 | C93: 11 | D93: 21 – 40
A94: Moderate | B94: 12 | C94: 15 | D94: 41 – 60
A95: Moderate to High | B95: 16 | C95: 19 | D95: 61 – 80
A96: High | B96: 20 | C96: 25 | D96: 81 – 100

Sheet Referensi_Threshold
A2: REFERENSI FORMULA & AMBANG BATAS (THRESHOLD) — PROJECT RISK & HEALTH DASHBOARD
A3: Nama Proyek: [lihat Config!B7] | Nama Perusahaan: [lihat Config!B6]
A5: 1. LIMA PILAR KESEHATAN PROYEK (PROJECT HEALTH) & FORMULA | L5: PARAMETER | M5: INDIKATOR | N5: KRITERIA HIJAU | O5: KRITERIA KUNING | P5: KRITERIA MERAH
A6: Pilar | B6: Indikator Utama | C6: Formula | D6: Bobot dalam PHS | E6: Sumber / Referensi | L6: Budget Performance | M6: Cost Variance (CV = EV - AC) | N6: CV ≥ 0 | O6: CV negatif ≤ 5% Budget | P6: CV negatif >5% Budget
A7: Financial Health | B7: Cost Performance Index (CPI) Cost Variance (CV) | C7: CPI = EV / AC CV = EV - AC | D7: =Config!B12 -> 0.2 | E7: Earned Value Management (EVM) - PMI Standard; ScheduleReader.com, 'Managing Project Health with SPI & CPI' | M7: Cost Performance Index (CPI = EV/AC) | N7: ≥1,00 | O7: 0,95–0,99 | P7: <0,95
A8: Schedule Health | B8: Schedule Performance Index (SPI) Schedule Variance (SV) | C8: SPI = EV / PV SV = EV - PV | D8: =Config!B13 -> 0.2 | E8: Earned Value Management (EVM) - PMI Standard; ScheduleReader.com | L8: Cash Flow Health | M8: Ketersediaan Dana terhadap kebutuhan 3 bulan | N8: ≥100% | O8: 80–99% | P8: <80%
A9: Supply Readiness Index (SRI) | B9: 5 parameter tertimbang pasokan (supply chain) | C9: SRI = S (Wi x Si) | D9: =Config!B14 -> 0.2 | E9: Pengelompokan Tahapan Pekerjaan Proyek (2025) | M9: Cash Flow Variance | N9: Deviasi ≤5% | O9: 5–10% | P9: >10%
A10: Project Execution Index (PEI) | B10: 4 parameter tertimbang pelaksanaan EPC | C10: PEI = S (Pj x Wj) | D10: =Config!B15 -> 0.2 | E10: praktik EPC Progress-S-Curve industri | L10: Forecast Cost | M10: Estimate at Completion (EAC) vs Approved Budget | N10: ≤100% Budget | O10: 100–105% | P10: >105%
A11: Commercial Readiness Index (CRI) | B11: 5 parameter tertimbang kesiapan komersial | C11: CRI = S (Wk x Sk) | D11: =Config!B16 -> 0.2 | M11: Forecast Cost Overrun | N11: <3% | O11: 3–10% | P11: >10%
L12: Funding Health | M12: Financing Availability | N12: Seluruh pendanaan tersedia | O12: Ada keterlambatan minor | P12: Belum tersedia/defisit dana
A13: Overall Project Health Score (PHS) | M13: Loan Drawdown Progress | N13: ≥95% sesuai rencana | O13: 80–94% | P13: <80%
A14: ="PHS = (FinancialScore x "&(Config!B12*100)&"%) + (ScheduleScore x "&(Config!B13*100)&"%) + (SRI x "&(Config!B14*100)&"%) + (PEI x "&(Config!B15*100)&"%) + (CRI x "&(Config!B16*100)&"%)" -> PHS = (FinancialScore x 20%) + (ScheduleScore x 20%) + (SRI x 20%) + (PEI x 20%) + (CRI x 20%) | L14: Payment Performance | M14: Progress Payment Delay | N14: ≤7 hari | O14: 8–30 hari | P14: >30 hari
A15: Catatan: FinancialScore & ScheduleScore dikonversi dari CPI/SPI. Jika indeks >= 1,00, skor = 100 (maksimal). Jika < 1,00, skor = indeks x 100. | M15: Outstanding Invoice | N15: <5% nilai kontrak | O15: 5–10% | P15: >10%
L16: Contingency Utilization | M16: Penggunaan Contingency Budget | N16: <50% | O16: 50–80% | P16: >80%
A17: 2. PARAMETER & BOBOT SUPPLY READINESS INDEX (SRI) | M17: Remaining Contingency | N17: >20% | O17: 10–20% | P17: <10%
A18: Parameter | B18: Bobot | C18: Deskripsi | F18: Justifikasi Bobot | L18: Contract & Claim Health | M18: Nilai Claim terhadap Contract Value | N18: <3% | O18: 3–10% | P18: >10%
A19: Salt Contract | B19: 0.25 | C19: Kepastian kontrak pasokan bahan baku garam industri jangka panjang dengan PT Garam maupun pemasok luar negeri. | F19: Fondasi suplai; tanpa kontrak jangka panjang, kontinuitas pabrik terancam (High Priority). | M19: Change Order Exposure | N19: <5% | O19: 5–10% | P19: >10%
A20: Salt Inventory | B20: 0.2 | C20: Kesiapan & kapasitas operasional gudang penyimpanan garam di pelabuhan dan lokasi pabrik. | F20: Buffer stok sangat krusial untuk mitigasi fluktuasi logistik laut/cuaca. | L20: Financial Risk Exposure | M20: Nilai Risiko Finansial (Expected Loss) | N20: Rendah | O20: Sedang | P20: Tinggi
A21: Supplier Qualification | B21: 0.15 | C21: Tingkat pemenuhan kualifikasi teknis dan standar kualitas garam dari para calon pemasok. | F21: Kualitas garam industri harus konsisten sesuai spesifikasi teknis peralatan. | M21: Risiko Nilai Tukar/Interest Rate | N21: Dalam batas toleransi | O21: Mendekati limit | P21: Melebihi limit
A22: Shipping Readiness | B22: 0.15 | C22: Kesiapan fasilitas pelabuhan, ketersediaan armada kapal logistik, dan jalur bongkar muat garam. | F22: Keterbatasan fasilitas pelabuhan atau kapal dapat memicu bottleneck rantai pasok. | L22: Investment Performance (Capex Project) | M22: NPV Forecast | N22: Positif | O22: Turun ≤10% | P22: Negatif
A23: Utility Readiness | B23: 0.15 | C23: Jaminan kesiapan tie-in pasokan gas bumi dari SKK Migas, air proses, uap panas, dan ketersediaan daya listrik. | F23: Pasokan utilitas (gas bumi/listrik) mutlak diperlukan sebelum Pre-Commissioning. | M23: IRR Forecast | N23: ≥Target | O23: Turun ≤2% | P23: Di bawah hurdle rate
A24: Salt Readiness | B24: 0.1 | C24: Fasilitas penanganan material (conveyor dan stockpile) serta integrasi dermaga harus terkalibrasi dan siap menerima suplai garam sebelum commissioning. | F24: Kesiapan infrastruktur material handling (conveyor/stockpile) di site sangat kritikal untuk menjamin kontinuitas suplai bahan baku utama (garam) tanpa bottleneck. | L24: Debt & Covenant | M24: DSCR Forecast | N24: ≥1,30 | O24: 1,10–1,29 | P24: <1,10
A25: TOTAL BOBOT SRI | B25: =SUM(B19:B24) -> 1 | C25: Harus = 1.00 (Berwarna merah jika total bobot salah) | M25: Covenant Compliance | N25: Seluruh covenant terpenuhi | O25: Mendekati threshold | P25: Pelanggaran covenant
A26: 3. PARAMETER & BOBOT PROJECT EXECUTION INDEX (PEI)
A27: Parameter | B27: Bobot | C27: Deskripsi | F27: Justifikasi Bobot
A28: Engineering Progress | B28: 0.2 | C28: Persentase penyelesaian gambar kerja detail (DED), dokumen spesifikasi teknis, dan persetujuan vendor drawings. | F28: Desain Engineering menentukan akurasi Procurement dan meminimalisir rework Konstruksi.
A29: Procurement Progress | B29: 0.3 | C29: Kemajuan pengadaan barang, khususnya long lead items (menara karbonasi, kiln dekomposisi, reaktor utama). | F29: Long Lead Items (kompresor, reaktor) merupakan penentu jalur kritis jadwal (Critical Path).
A30: Construction Progress | B30: 0.3 | C30: Kemajuan fisik konstruksi sipil, pondasi alat berat, struktur baja, instalasi mekanikal, kelistrikan, pemipaan. | F30: Pekerjaan sipil & mekanikal memiliki porsi man-hours terbesar dalam siklus EPC.
A31: Commissioning Preparation | B31: 0.1 | C31: Penyelesaian dokumen prosedur pengujian, tim start-up, Loop Test instrumen, dan suku cadang awal operasional. | F31: Dokumentasi prosedur (SOP) harus siap sebelum tahapan Mechanical Completion.
A32: Pencapaian Performance Test | B32: 0.1 | C32: Plant harus didemonstrasikan mampu beroperasi stabil pada beban maksimal (misal: 72 jam berturut-turut) untuk tahap serah terima (handover). | F32: Validasi akhir bahwa pabrik mampu beroperasi sesuai kapasitas desain (Nameplate Capacity) merupakan syarat mutlak komersialisasi dan pencapaian target finansial.
A33: TOTAL BOBOT PEI | B33: =SUM(B28:B32) -> 1 | C33: Harus = 1.00 (Berwarna merah jika total bobot salah)
A34: 4. PARAMETER & BOBOT COMMERCIAL READINESS INDEX (CRI)
A35: Parameter | B35: Bobot | C35: Deskripsi | F35: Justifikasi Bobot
A36: Offtake Agreement | B36: 0.2 | C36: Jumlah volume produk yang telah terikat dalam nota kesepahaman (MOU/Offtake Agreement) dengan pembeli domestik. | F36: Perjanjian jual beli (Offtake) memastikan kepastian arus kas saat fase operasi dimulai.
A37: Marketing Strategy | B37: 0.2 | C37: Kesiapan strategi penetapan harga kompetitif terhadap produk impor dan diversifikasi varian produk. | F37: Strategi penetapan harga kompetitif untuk penetrasi pasar domestik vs impor.
A38: Distribution Readiness | B38: 0.1 | C38: Kesiapan logistik pengiriman produk akhir: bagging unit, armada pengangkutan darat, konveyor pelabuhan. | F38: Kesiapan armada logistik, gudang produk jadi, dan skema distribusi ke pelanggan.
A39: Operation Team Ready | B39: 0.2 | C39: Kesiapan tim operasi pabrik: sertifikasi operator, SOP pengoperasian, pelatihan simulasi kondisi darurat. | F39: Sertifikasi dan pelatihan operator (O&M) untuk menjamin Plant Safety.
A40: Product Qualification | B40: 0.2 | C40: Kesiapan laboratorium pengujian mutu produk & sertifikasi SNI agar memenuhi kualifikasi industri premium. | F40: Lisensi operasi dan izin lingkungan (AMDAL) adalah prasyarat hukum mutlak (Go/No-Go).
A41: Regulatory Readiness | B41: 0.1 | C41: Seluruh dokumen Izin Usaha Industri (IUI) dan sertifikasi layak operasi (SLO) harus diterbitkan sebelum dimulainya produksi komersial untuk menghindari sanksi penutupan. | F41: Kepatuhan terhadap regulasi pemerintah sangat menentukan legalitas operasi; keterlambatan izin akan menghentikan seluruh proses produksi terlepas dari kesiapan teknis pabrik.
A42: TOTAL BOBOT CRI | B42: =SUM(B36:B41) -> 1 | C42: Harus = 1.00 (Berwarna merah jika total bobot salah)
A43: 5. TABEL BATAS TOLERANSI (THRESHOLD) - SISTEM RAG (RED-AMBER-GREEN)
A44: Pilar Kesehatan | B44: Indikator | C44: Hijau | D44: Kuning | E44: Oranye | F44: Merah
A45: Financial Health | B45: CPI | C45: ="CPI >= "&ROUND(Config!B42, 2) -> CPI >= 1 | D45: ="CPI "&ROUND(Config!B43, 2)&" – "&ROUND(Config!B42-0.01, 2) -> CPI 0,95 – 0,99 | E45: ="CPI "&ROUND(Config!B44, 2)&" – "&ROUND(Config!B43-0.01, 2) -> CPI 0,9 – 0,94 | F45: ="CPI < "&ROUND(Config!B44, 2) -> CPI < 0,9
A46: Schedule Health | B46: SPI | C46: ="SPI >= "&ROUND(Config!B45, 2) -> SPI >= 1 | D46: ="SPI "&ROUND(Config!B46, 2)&" – "&ROUND(Config!B45-0.01, 2) -> SPI 0,95 – 0,99 | E46: ="SPI "&ROUND(Config!B47, 2)&" – "&ROUND(Config!B46-0.01, 2) -> SPI 0,9 – 0,94 | F46: ="SPI < "&ROUND(Config!B47, 2) -> SPI < 0,9
A47: Supply Readiness | B47: SRI | C47: ="SRI >= "&Config!B48&"%" -> SRI >= 90% | D47: ="SRI "&Config!B49&" – "&(Config!B48-1)&"%" -> SRI 75 – 89% | E47: ="SRI "&Config!B50&" – "&(Config!B49-1)&"%" -> SRI 65 – 74% | F47: ="SRI < "&Config!B50&"%" -> SRI < 65%
A48: Project Execution | B48: PEI (Deviasi Fisik) | C48: ="PEI >= "&Config!B51&"%" -> PEI >= 90% | D48: ="PEI "&Config!B52&" – "&(Config!B51-1)&"%" -> PEI 80 – 89% | E48: ="PEI "&Config!B53&" – "&(Config!B52-1)&"%" -> PEI 70 – 79% | F48: ="PEI < "&Config!B53&"%" -> PEI < 70%
A49: Commercial Readiness | B49: CRI | C49: ="CRI >= "&Config!B54&"%" -> CRI >= 80% | D49: ="CRI "&Config!B55&" – "&(Config!B54-1)&"%" -> CRI 60 – 79% | E49: ="CRI "&Config!B56&" – "&(Config!B55-1)&"%" -> CRI 50 – 59% | F49: ="CRI < "&Config!B56&"%" -> CRI < 50%
A50: Overall Health | B50: PHS | C50: ="PHS "&Config!B57&" – 100%" -> PHS 90 – 100% | D50: ="PHS "&Config!B58&" – "&(Config!B57-1)&"%" -> PHS 80 – 89% | E50: ="PHS "&Config!B59&" – "&(Config!B58-1)&"%" -> PHS 70 – 79% | F50: ="PHS < "&Config!B59&"%" -> PHS < 70%
A52: 6. KRITERIA LIKELIHOOD (PROBABILITAS) - MATRIKS RISIKO 5x5
A53: Catatan: kriteria berikut merupakan kriteria standar manajemen risiko (ISO 31000 & benchmark RCSA/KRI). Sesuaikan dengan resmi apabila tersedia angka baku internal.
A54: Level (L) | B54: Kategori | C54: Kriteria Probabilitas Kejadian
A55: 1 | B55: =Config!B72 -> Sangat Jarang Terjadi | C55: ="Kemungkinan terjadi "&Config!C72&"; "&Config!D72 -> Kemungkinan terjadi < 10%; Hampir tidak pernah terjadi selama siklus proyek
A56: 2 | B56: =Config!B73 -> Jarang Terjadi | C56: ="Kemungkinan terjadi "&Config!C73&"; "&Config!D73 -> Kemungkinan terjadi 10 – 30%; Pernah terjadi, namun jarang
A57: 3 | B57: =Config!B74 -> Bisa Terjadi | C57: ="Kemungkinan terjadi "&Config!C74&"; "&Config!D74 -> Kemungkinan terjadi 30 – 50%; Pernah terjadi beberapa kali
A58: 4 | B58: =Config!B75 -> Sangat Mungkin Terjadi | C58: ="Kemungkinan terjadi "&Config!C75&"; "&Config!D75 -> Kemungkinan terjadi 50 – 70%; Kondisi & indikasi sudah muncul
A59: 5 | B59: =Config!B76 -> Hampir Pasti Terjadi | C59: ="Kemungkinan terjadi "&Config!C76&"; "&Config!D76 -> Kemungkinan terjadi > 70%; Sudah terdapat indikasi kuat akan terjadi
A61: 7. KRITERIA CONSEQUENCE (DAMPAK) - MATRIKS RISIKO 5x5
A62: Level (C) | B62: Kategori | C62: Kriteria Dampak (Finansial / Jadwal / Reputasi)
A63: 1 | B63: =Config!B82 -> Sangat Rendah | C63: =Config!C82 & " ; " & Config!D82 -> Dampak biaya dapat diabaikan (< USD 0.5 Jt) ; Tidak ada keterlambatan signifikan (maks 1 bln)
A64: 2 | B64: =Config!B83 -> Rendah | C64: =Config!C83 & " ; " & Config!D83 -> Dampak biaya minor (USD 0.5 - 2 Jt) ; Keterlambatan minor (hingga 3 bln)
A65: 3 | B65: =Config!B84 -> Moderat | C65: =Config!C84 & " ; " & Config!D84 -> Dampak biaya moderat (USD 2 - 10 Jt) ; Keterlambatan berdampak pada jadwal utama (hingga 6 bln)
A66: 4 | B66: =Config!B85 -> Tinggi | C66: =Config!C85 & " ; " & Config!D85 -> Dampak biaya signifikan (USD 10 - 30 Jt) ; Keterlambatan penyelesaian proyek (hingga 12 bln)
A67: 5 | B67: =Config!B86 -> Sangat Tinggi | C67: =Config!C86 & " ; " & Config!D86 -> Dampak biaya krisis (> USD 30 Jt) ; Proyek terancam batal / sangat terlambat (> 24 bln)
A69: 8. KLASIFIKASI LEVEL RISIKO - 5 TINGKAT
A70: Skor Matriks L x C TIDAK lagi dihitung dari perkalian langsung L x C dengan pembagian rentang rata, melainkan menggunakan Tabel Skala Risiko Non-Linear (Skala 1-25) pada bagian 10 di bawah, yang memprioritaskan bobot Consequence (Dampak) dibanding Likelihood (Probabilitas) untuk kombinasi bernilai sama — konsisten dengan pendekatan penentuan level risiko non-linear yang lazim digunakan pada matriks 5x5 ISO 31000:2018 / AS-NZS ISO 31000 dan praktik matriks risiko K3/SMKP BUMN sektor energi-tambang (rujukan pola: Kepdirjen Minerba No.1827.K/30/MEM/2018). Overall Risk Index (skala 0-100, benchmark ) tetap memakai rentang rata seperti semula.
A71: Level Risiko | B71: Skor Matriks L x C (1-25) | C71: Overall Risk Index (0-100)
A72: =Config!A92 -> Low | B72: =Config!B92&" - "&Config!C92 -> 1 - 5 | C72: =Config!D92 -> 0 – 20
A73: =Config!A93 -> Low to Moderate | B73: =Config!B93&" - "&Config!C93 -> 6 - 11 | C73: =Config!D93 -> 21 – 40
A74: =Config!A94 -> Moderate | B74: =Config!B94&" - "&Config!C94 -> 12 - 15 | C74: =Config!D94 -> 41 – 60
A75: =Config!A95 -> Moderate to High | B75: =Config!B95&" - "&Config!C95 -> 16 - 19 | C75: =Config!D95 -> 61 – 80
A76: =Config!A96 -> High | B76: =Config!B96&" - "&Config!C96 -> 20 - 25 | C76: =Config!D96 -> 81 – 100
A78: 9. KOMPOSISI SUB-INDEKS OVERALL RISK INDEX
A79: Supply Risk Index | B79: =Config!B21 -> 0.4 | C79: Bahan baku garam industri, kualitas garam lokal vs impor, keandalan pemasok, risiko logistik maritim, kesiapan gudang, kesiapan utilitas.
A80: Execution Risk Index | B80: =Config!B22 -> 0.4 | C80: Kesiapan rekayasa desain, pengadaan peralatan utama, produktivitas tenaga kerja, antarmuka antar-EPC, pengapalan long lead items, kesiapan uji fungsi.
A81: Commercial Risk Index | B81: =Config!B23 -> 0.2 | C81: Pengikatan kontrak offtake, fluktuasi harga global, tekanan produk impor, kesiapan logistik distribusi hilir, sertifikasi kualitas produk.
A82: Overall Risk Index = (Supply Risk Index × Bobot Supply) + (Execution Risk Index × Bobot Eksekusi) + (Commercial Risk Index × Bobot Komersial)
A84: Sumber benchmark tata kelola risiko: PT (Persero) - Direktorat Manajemen Risiko (2nd Line of Defense, Permen BUMN No.02/2023), Komite Tata Kelola Terintegrasi (KTKT), Gate Review/FID, RCSA, KRI, ICT, C-RBDD; PT Biro Klasifikasi Indonesia (Persero) - SK-6/2023 (Risk Appetite berbasis Net Working Capital); klasifikasi 5-tingkat Low/Low to Moderate/Moderate/Moderate to High/High mengikuti nomenklatur .
A89: 10. TABEL SKALA RISIKO (RISK RANKING) 5x5 NON-LINEAR & WARNA HEAT MAP
A90: Tabel skala risiko berikut menetapkan urutan (rank) 1-25 untuk setiap 25 kombinasi Likelihood (L) x Consequence (C) sesuai spesifikasi metodologi risiko internal yang ditetapkan Project Control . Berbeda dari perkalian L x C sederhana, urutan ini memberi bobot lebih besar pada Consequence saat terjadi nilai sama, mengikuti kaidah umum non-linear risk ranking pada standar ISO 31000:2018 dan praktik matriks risiko korporasi BUMN. Skala menentukan posisi & warna sel pada Risk Profile Heat Map di sheet Dashboard.
A92: Key (L x10 + C) | B92: L (1-5) | C92: C (1-5) | D92: Skala (1-25) | E92: Level Risiko | F92: Kode Warna (Hex)
A93: 11 | B93: 1 | C93: 1 | D93: 1 | E93: Low | F93: #538135
A94: 21 | B94: 2 | C94: 1 | D94: 2 | E94: Low | F94: #538135
A95: 31 | B95: 3 | C95: 1 | D95: 3 | E95: Low | F95: #538135
A96: 41 | B96: 4 | C96: 1 | D96: 4 | E96: Low | F96: #538135
A97: 12 | B97: 1 | C97: 2 | D97: 5 | E97: Low | F97: #538135
A98: 22 | B98: 2 | C98: 2 | D98: 6 | E98: Low to Moderate | F98: #A9D18E
A99: 51 | B99: 5 | C99: 1 | D99: 7 | E99: Low to Moderate | F99: #A9D18E
A100: 32 | B100: 3 | C100: 2 | D100: 8 | E100: Low to Moderate | F100: #A9D18E
A101: 42 | B101: 4 | C101: 2 | D101: 9 | E101: Low to Moderate | F101: #A9D18E
A102: 13 | B102: 1 | C102: 3 | D102: 10 | E102: Low to Moderate | F102: #A9D18E
A103: 23 | B103: 2 | C103: 3 | D103: 11 | E103: Low to Moderate | F103: #A9D18E
A104: 52 | B104: 5 | C104: 2 | D104: 12 | E104: Moderate | F104: #FFD966
... A117: 55 | B117: 5 | C117: 5 | D117: 25 | E117: High | F117: #E06666
A119: Sumber/Referensi Tabel Skala: metodologi non-linear risk ranking ISO 31000:2018 (klausul 5.4.3 - penentuan level risiko); praktik matriks 5x5 K3/SMKP BUMN sektor energi & tambang; disesuaikan dengan nomenklatur 5-tingkat (Low / Low to Moderate / Moderate / Moderate to High / High).
A121: 11. METODOLOGI EARLY WARNING SYSTEM (EWS) — 3 STATUS (AMAN / WASPADA / BAHAYA)
A122: Setiap parameter EWS diklasifikasikan ke 3 status menggunakan pendekatan Key Risk Indicator (KRI) Traffic Light dengan buffer toleransi 10% dari threshold sebagai batas Waspada (Amber Zone), mengacu pada COSO Enterprise Risk Management Framework (2017) dan praktik RCSA-KRI PT (Persero) yang telah dirujuk pada dokumen ini.
A124: Status | B124: Definisi Ambang Batas (untuk indikator "semakin tinggi semakin baik") | E124: Warna
A125: Aman | B125: Nilai Aktual >= Threshold (batas aman terpenuhi)
A126: Waspada | B126: ="Threshold × (1 - "&TEXT(Config!B29/100,"0%")&") <= Nilai Aktual < Threshold" -> #VALUE!
A127: Bahaya | B127: ="Nilai Aktual < Threshold × (1 - "&TEXT(Config!B29/100,"0%")&")" -> #VALUE!
...

Sheet Dashboard
B1: PROJECT RISK & HEALTH DASHBOARD
B2: ="Reporting Period: "&TEXT(Input_Bulanan!D5, "mmmm yyyy")&" | Status: "&Input_Bulanan!F5&" | Dicetak: "&TEXT(TODAY(), "DD-MM-YYYY") -> Reporting Period: November 2026 | Status: Final | Dicetak: 24-07-2026
B4: PANEL A - PROJECT HEALTH OVERVIEW (Retrospective Performance) | M4: PANEL B - CURRENT RISK EXPOSURE (Prospective Threats)
B5: Overall Project Health Score (PHS) | G5: Sub-Index Readiness & Performance | M5: Overall Risk Level (Composite) | R5: Risk Profile Heat Map (Likelihood x Consequence)
B6: =((IF(Input_Bulanan!D12>=1,100,Input_Bulanan!D12*100)*Config!B12)+(IF(Input_Bulanan!D14>=1,100,Input_Bulanan!D14*100)*Config!B13)+(Input_Bulanan!D24*100*Config!B14)+(Input_Bulanan!D32*100*Config!B15)+(Input_Bulanan!D42*100*Config!B16))/100 -> 0.8276 | G6: Supply Readiness Index (SRI) | K6: =Input_Bulanan!D24 -> 0.805 | M6: =Input_Bulanan!D49 -> Moderate to High | R6: L=5 | S6: =IF(AND(Input_Bulanan!$G$75=1,Input_Bulanan!$F$75=5),Input_Bulanan!$C$75,IF(AND(Input_Bulanan!$G$76=1,Input_Bulanan!$F$76=5),Input_Bulanan!$C$76,IF(AND(Input_Bulanan!$G$77=1,Input_Bulanan!$F$77=5),Input_Bulanan!$C$77,IF(AND(Input_Bulanan!$G$78=1,Input_Bulanan!$F$78=5),Input_Bulanan!$C$78,"")))) | T6: =IF(AND(Input_Bulanan!$G$75=2,Input_Bulanan!$F$75=5),Input_Bulanan!$C$75,IF(AND(Input_Bulanan!$G$76=2,Input_Bulanan!$F$76=5),Input_Bulanan!$C$76,IF(AND(Input_Bulanan!$G$77=2,Input_Bulanan!$F$77=5),Input_Bulanan!$C$77,IF(AND(Input_Bulanan!$G$78=2,Input_Bulanan!$F$78=5),Input_Bulanan!$C$78,"")))) | U6: =IF(AND(Input_Bulanan!$G$75=3,Input_Bulanan!$F$75=5),Input_Bulanan!$C$75,IF(AND(Input_Bulanan!$G$76=3,Input_Bulanan!$F$76=5),Input_Bulanan!$C$76,IF(AND(Input_Bulanan!$G$77=3,Input_Bulanan!$F$77=5),Input_Bulanan!$C$77,IF(AND(Input_Bulanan!$G$78=3,Input_Bulanan!$F$78=5),Input_Bulanan!$C$78,"")))) | V6: =IF(AND(Input_Bulanan!$G$75=4,Input_Bulanan!$F$75=5),Input_Bulanan!$C$75,IF(AND(Input_Bulanan!$G$76=4,Input_Bulanan!$F$76=5),Input_Bulanan!$C$76,IF(AND(Input_Bulanan!$G$77=4,Input_Bulanan!$F$77=5),Input_Bulanan!$C$77,IF(AND(Input_Bulanan!$G$78=4,Input_Bulanan!$F$78=5),Input_Bulanan!$C$78,"")))) | W6: =IF(AND(Input_Bulanan!$G$75=5,Input_Bulanan!$F$75=5),Input_Bulanan!$C$75,IF(AND(Input_Bulanan!$G$76=5,Input_Bulanan!$F$76=5),Input_Bulanan!$C$76,IF(AND(Input_Bulanan!$G$77=5,Input_Bulanan!$F$77=5),Input_Bulanan!$C$77,IF(AND(Input_Bulanan!$G$78=5,Input_Bulanan!$F$78=5),Input_Bulanan!$C$78,""))))
R7: L=4 | S7: =IF(AND(Input_Bulanan!$G$75=1,Input_Bulanan!$F$75=4),Input_Bulanan!$C$75,IF(AND(Input_Bulanan!$G$76=1,Input_Bulanan!$F$76=4),Input_Bulanan!$C$76,IF(AND(Input_Bulanan!$G$77=1,Input_Bulanan!$F$77=4),Input_Bulanan!$C$77,IF(AND(Input_Bulanan!$G$78=1,Input_Bulanan!$F$78=4),Input_Bulanan!$C$78,"")))) | T7: =IF(AND(Input_Bulanan!$G$75=2,Input_Bulanan!$F$75=4),Input_Bulanan!$C$75,IF(AND(Input_Bulanan!$G$76=2,Input_Bulanan!$F$76=4),Input_Bulanan!$C$76,IF(AND(Input_Bulanan!$G$77=2,Input_Bulanan!$F$77=4),Input_Bulanan!$C$77,IF(AND(Input_Bulanan!$G$78=2,Input_Bulanan!$F$78=4),Input_Bulanan!$C$78,"")))) | U7: =IF(AND(Input_Bulanan!$G$75=3,Input_Bulanan!$F$75=4),Input_Bulanan!$C$75,IF(AND(Input_Bulanan!$G$76=3,Input_Bulanan!$F$76=4),Input_Bulanan!$C$76,IF(AND(Input_Bulanan!$G$77=3,Input_Bulanan!$F$77=4),Input_Bulanan!$C$77,IF(AND(Input_Bulanan!$G$78=3,Input_Bulanan!$F$78=4),Input_Bulanan!$C$78,"")))) | V7: =IF(AND(Input_Bulanan!$G$75=4,Input_Bulanan!$F$75=4),Input_Bulanan!$C$75,IF(AND(Input_Bulanan!$G$76=4,Input_Bulanan!$F$76=4),Input_Bulanan!$C$76,IF(AND(Input_Bulanan!$G$77=4,Input_Bulanan!$F$77=4),Input_Bulanan!$C$77,IF(AND(Input_Bulanan!$G$78=4,Input_Bulanan!$F$78=4),Input_Bulanan!$C$78,"")))) -> C3 | W7: =IF(AND(Input_Bulanan!$G$75=5,Input_Bulanan!$F$75=4),Input_Bulanan!$C$75,IF(AND(Input_Bulanan!$G$76=5,Input_Bulanan!$F$76=4),Input_Bulanan!$C$76,IF(AND(Input_Bulanan!$G$77=5,Input_Bulanan!$F$77=4),Input_Bulanan!$C$77,IF(AND(Input_Bulanan!$G$78=5,Input_Bulanan!$F$78=4),Input_Bulanan!$C$78,"")))) -> C1
G8: Project Execution Index (PEI) | K8: =Input_Bulanan!D32 -> 0.723 | R8: L=3 | S8: =IF(AND(Input_Bulanan!$G$75=1,Input_Bulanan!$F$75=3),Input_Bulanan!$C$75,IF(AND(Input_Bulanan!$G$76=1,Input_Bulanan!$F$76=3),Input_Bulanan!$C$76,IF(AND(Input_Bulanan!$G$77=1,Input_Bulanan!$F$77=3),Input_Bulanan!$C$77,IF(AND(Input_Bulanan!$G$78=1,Input_Bulanan!$F$78=3),Input_Bulanan!$C$78,"")))) | T8: =IF(AND(Input_Bulanan!$G$75=2,Input_Bulanan!$F$75=3),Input_Bulanan!$C$75,IF(AND(Input_Bulanan!$G$76=2,Input_Bulanan!$F$76=3),Input_Bulanan!$C$76,IF(AND(Input_Bulanan!$G$77=2,Input_Bulanan!$F$77=3),Input_Bulanan!$C$77,IF(AND(Input_Bulanan!$G$78=2,Input_Bulanan!$F$78=3),Input_Bulanan!$C$78,"")))) | U8: =IF(AND(Input_Bulanan!$G$75=3,Input_Bulanan!$F$75=3),Input_Bulanan!$C$75,IF(AND(Input_Bulanan!$G$76=3,Input_Bulanan!$F$76=3),Input_Bulanan!$C$76,IF(AND(Input_Bulanan!$G$77=3,Input_Bulanan!$F$77=3),Input_Bulanan!$C$77,IF(AND(Input_Bulanan!$G$78=3,Input_Bulanan!$F$78=3),Input_Bulanan!$C$78,"")))) -> C4 | V8: =IF(AND(Input_Bulanan!$G$75=4,Input_Bulanan!$F$75=3),Input_Bulanan!$C$75,IF(AND(Input_Bulanan!$G$76=4,Input_Bulanan!$F$76=3),Input_Bulanan!$C$76,IF(AND(Input_Bulanan!$G$77=4,Input_Bulanan!$F$77=3),Input_Bulanan!$C$77,IF(AND(Input_Bulanan!$G$78=4,Input_Bulanan!$F$78=3),Input_Bulanan!$C$78,"")))) | W8: =IF(AND(Input_Bulanan!$G$75=5,Input_Bulanan!$F$75=3),Input_Bulanan!$C$75,IF(AND(Input_Bulanan!$G$76=5,Input_Bulanan!$F$76=3),Input_Bulanan!$C$76,IF(AND(Input_Bulanan!$G$77=5,Input_Bulanan!$F$77=3),Input_Bulanan!$C$77,IF(AND(Input_Bulanan!$G$78=5,Input_Bulanan!$F$78=3),Input_Bulanan!$C$78,""))))
R9: L=2 | S9: =IF(AND(Input_Bulanan!$G$75=1,Input_Bulanan!$F$75=2),Input_Bulanan!$C$75,IF(AND(Input_Bulanan!$G$76=1,Input_Bulanan!$F$76=2),Input_Bulanan!$C$76,IF(AND(Input_Bulanan!$G$77=1,Input_Bulanan!$F$77=2),Input_Bulanan!$C$77,IF(AND(Input_Bulanan!$G$78=1,Input_Bulanan!$F$78=2),Input_Bulanan!$C$78,"")))) | T9: =IF(AND(Input_Bulanan!$G$75=2,Input_Bulanan!$F$75=2),Input_Bulanan!$C$75,IF(AND(Input_Bulanan!$G$76=2,Input_Bulanan!$F$76=2),Input_Bulanan!$C$76,IF(AND(Input_Bulanan!$G$77=2,Input_Bulanan!$F$77=2),Input_Bulanan!$C$77,IF(AND(Input_Bulanan!$G$78=2,Input_Bulanan!$F$78=2),Input_Bulanan!$C$78,"")))) | U9: =IF(AND(Input_Bulanan!$G$75=3,Input_Bulanan!$F$75=2),Input_Bulanan!$C$75,IF(AND(Input_Bulanan!$G$76=3,Input_Bulanan!$F$76=2),Input_Bulanan!$C$76,IF(AND(Input_Bulanan!$G$77=3,Input_Bulanan!$F$77=2),Input_Bulanan!$C$77,IF(AND(Input_Bulanan!$G$78=3,Input_Bulanan!$F$78=2),Input_Bulanan!$C$78,"")))) | V9: =IF(AND(Input_Bulanan!$G$75=4,Input_Bulanan!$F$75=2),Input_Bulanan!$C$75,IF(AND(Input_Bulanan!$G$76=4,Input_Bulanan!$F$76=2),Input_Bulanan!$C$76,IF(AND(Input_Bulanan!$G$77=4,Input_Bulanan!$F$77=2),Input_Bulanan!$C$77,IF(AND(Input_Bulanan!$G$78=4,Input_Bulanan!$F$78=2),Input_Bulanan!$C$78,"")))) | W9: =IF(AND(Input_Bulanan!$G$75=5,Input_Bulanan!$F$75=2),Input_Bulanan!$C$75,IF(AND(Input_Bulanan!$G$76=5,Input_Bulanan!$F$76=2),Input_Bulanan!$C$76,IF(AND(Input_Bulanan!$G$77=5,Input_Bulanan!$F$77=2),Input_Bulanan!$C$77,IF(AND(Input_Bulanan!$G$78=5,Input_Bulanan!$F$78=2),Input_Bulanan!$C$78,""))))
B10: =IF(B6>=0.9,"HIJAU - SEHAT",IF(B6>=0.75,"KUNING - PANTAU",IF(B6>=0.6,"ORANYE - WASPADA","MERAH - KRITIS"))) -> KUNING - PANTAU | G10: Commercial Readiness Index (CRI) | K10: =Input_Bulanan!D42 -> 0.61 | M10: ="Skor Komposit: "&TEXT(Input_Bulanan!D48,"0,00")&" / 100" -> Skor Komposit: 73,32 / 100 | R10: L=1 | S10: =IF(AND(Input_Bulanan!$G$75=1,Input_Bulanan!$F$75=1),Input_Bulanan!$C$75,IF(AND(Input_Bulanan!$G$76=1,Input_Bulanan!$F$76=1),Input_Bulanan!$C$76,IF(AND(Input_Bulanan!$G$77=1,Input_Bulanan!$F$77=1),Input_Bulanan!$C$77,IF(AND(Input_Bulanan!$G$78=1,Input_Bulanan!$F$78=1),Input_Bulanan!$C$78,"")))) | T10: =IF(AND(Input_Bulanan!$G$75=2,Input_Bulanan!$F$75=1),Input_Bulanan!$C$75,IF(AND(Input_Bulanan!$G$76=2,Input_Bulanan!$F$76=1),Input_Bulanan!$C$76,IF(AND(Input_Bulanan!$G$77=2,Input_Bulanan!$F$77=1),Input_Bulanan!$C$77,IF(AND(Input_Bulanan!$G$78=2,Input_Bulanan!$F$78=1),Input_Bulanan!$C$78,"")))) | U10: =IF(AND(Input_Bulanan!$G$75=3,Input_Bulanan!$F$75=1),Input_Bulanan!$C$75,IF(AND(Input_Bulanan!$G$76=3,Input_Bulanan!$F$76=1),Input_Bulanan!$C$76,IF(AND(Input_Bulanan!$G$77=3,Input_Bulanan!$F$77=1),Input_Bulanan!$C$77,IF(AND(Input_Bulanan!$G$78=3,Input_Bulanan!$F$78=1),Input_Bulanan!$C$78,"")))) | V10: =IF(AND(Input_Bulanan!$G$75=4,Input_Bulanan!$F$75=1),Input_Bulanan!$C$75,IF(AND(Input_Bulanan!$G$76=4,Input_Bulanan!$F$76=1),Input_Bulanan!$C$76,IF(AND(Input_Bulanan!$G$77=4,Input_Bulanan!$F$77=1),Input_Bulanan!$C$77,IF(AND(Input_Bulanan!$G$78=4,Input_Bulanan!$F$78=1),Input_Bulanan!$C$78,"")))) | W10: =IF(AND(Input_Bulanan!$G$75=5,Input_Bulanan!$F$75=1),Input_Bulanan!$C$75,IF(AND(Input_Bulanan!$G$76=5,Input_Bulanan!$F$76=1),Input_Bulanan!$C$76,IF(AND(Input_Bulanan!$G$77=5,Input_Bulanan!$F$77=1),Input_Bulanan!$C$77,IF(AND(Input_Bulanan!$G$78=5,Input_Bulanan!$F$78=1),Input_Bulanan!$C$78,""))))
R11: C -> | S11: 1 | T11: 2 | U11: 3 | V11: 4 | W11: 5
B12: Key Financial & Schedule | G12: Master Schedule S-Curve (USD Juta) | M12: Risk Register - Risiko Aktif | R12: Legenda Top Risk
B13: Cost Performance Index (CPI) | E13: =Input_Bulanan!D12 -> 2 | G13: Planned Value (PV) | J13: =Input_Bulanan!D8 -> 1000 | M13: High | P13: =Input_Bulanan!D52 -> 5 | R13: =Input_Bulanan!C75 -> C1 | S13: =Input_Bulanan!D75&" | L="&Input_Bulanan!F75&", C="&Input_Bulanan!G75&", Skala="&Input_Bulanan!H75&" -> "&Input_Bulanan!I75 -> Salt Supply Disruption (gangguan pasokan garam industri) | L=4, C=5, Skala=24 -> High
B14: Schedule Performance Index (SPI) | E14: =Input_Bulanan!D14 -> 1 | G14: Earned Value (EV) | J14: =Input_Bulanan!D9 -> 1000 | M14: Moderate to High | P14: =Input_Bulanan!D53 -> 11 | R14: =Input_Bulanan!C76 -> C2 | S14: =Input_Bulanan!D76&" | L="&Input_Bulanan!F76&", C="&Input_Bulanan!G76&", Skala="&Input_Bulanan!H76&" -> "&Input_Bulanan!I76 -> Commissioning Delay (keterlambatan commissioning) | L=4, C=5, Skala=24 -> High
B15: Cost Variance (CV), USD Juta | E15: =Input_Bulanan!D13 -> 500 | G15: Actual Cost (AC) | J15: =Input_Bulanan!D10 -> 500 | M15: Moderate | P15: =Input_Bulanan!D54 -> 18 | R15: =Input_Bulanan!C77 -> C3 | S15: =Input_Bulanan!D77&" | L="&Input_Bulanan!F77&", C="&Input_Bulanan!G77&", Skala="&Input_Bulanan!H77&" -> "&Input_Bulanan!I77 -> EPC Interface Issue (isu EPC interface lintas kontraktor) | L=4, C=4, Skala=19 -> Moderate to High
B16: Schedule Variance (SV), USD Juta | E16: =Input_Bulanan!D15 -> 0 | G16: (Bar proporsional: lihat conditional formatting / grafik pada versi HTML) | M16: Low to Moderate | P16: =Input_Bulanan!D55 -> 4 | R16: =Input_Bulanan!C78 -> C4 | S16: =Input_Bulanan!D78&" | L="&Input_Bulanan!F78&", C="&Input_Bulanan!G78&", Skala="&Input_Bulanan!H78&" -> "&Input_Bulanan!I78 -> Long Lead Equipment (keterlambatan peralatan utama) | L=3, C=3, Skala=13 -> Moderate
M17: Low | P17: =Input_Bulanan!D56 -> 3
M18: Total Risiko Aktif | P18: =Input_Bulanan!D57 -> 41
B20: Catatan Metodologi | M20: Mitigation Health Progress
M21: Completed Mitigations | P21: =Input_Bulanan!D60 -> 0.82
M22: On Track Mitigations | P22: =Input_Bulanan!D61 -> 0.18
M23: Overdue Actions | P23: =Input_Bulanan!D62 -> 0.76
M24: Need Escalation (jumlah aksi) | P24: =Input_Bulanan!D63 -> 5
B26: PANEL C - EARLY WARNING SYSTEM (EWS) ALERTS
B27: Parameter | G27: Threshold | K27: Aktual | M27: Aman | N27: Waspada | O27: Bahaya | P27: Implikasi Operasional & Finansial
B28: =Input_Bulanan!C67 -> First Shipment | G28: =Input_Bulanan!D67 -> Target: 1 Nov 27 (Lower is better) | K28: =TEXT(Input_Bulanan!E67,"dd-mmm-yy") -> 03-Oct-27 | M28: =IF(Input_Bulanan!H67="Aman","V","") | N28: =IF(Input_Bulanan!H67="Waspada","V","") -> V | O28: =IF(Input_Bulanan!H67="Bahaya","V","") | P28: Keterlambatan pengiriman pertama berpotensi memicu klaim dari Offtaker utama.
B29: =Input_Bulanan!C68 -> Project Progress | G29: =Input_Bulanan!D68 -> Minimal 90% (Higher is better) | K29: =TEXT(Input_Bulanan!E68,"0%") -> 90% | M29: =IF(Input_Bulanan!H68="Aman","V","") -> V | N29: =IF(Input_Bulanan!H68="Waspada","V","") | O29: =IF(Input_Bulanan!H68="Bahaya","V","") | P29: Keterlambatan progres berpotensi menunda tahap commissioning.
B30: =Input_Bulanan!C69 -> Offtaker Agreement | G30: =Input_Bulanan!D69 -> Target SPI >= 1.00 (Higher is better) | K30: =TEXT(Input_Bulanan!E69,"0%") -> 90% | M30: =IF(Input_Bulanan!H69="Aman","V","") | N30: =IF(Input_Bulanan!H69="Waspada","V","") -> V | O30: =IF(Input_Bulanan!H69="Bahaya","V","") | P30: Belum tercapainya kuota offtake minimal mengancam kelayakan finansial operasi.
B35: PANEL D - EXECUTIVE ACTIONS & DECISION REQUIRED
B36: ="Prioritas 1—2: [1] " & INDEX(Risk_Action_Tracker!E$6:E$15, MATCH(LARGE(Risk_Action_Tracker!Z$6:Z$15, 1), Risk_Action_Tracker!Z$6:Z$15, 0)) & " · [2] " & INDEX(Risk_Action_Tracker!E$6:E$15, MATCH(LARGE(Risk_Action_Tracker!Z$6:Z$15, 2), Risk_Action_Tracker!Z$6:Z$15, 0)) -> Prioritas 1—2: [1] Mengesahkan pembentukan tim Interface Coordinator dan menerapkan Interface Management Plan (IMP) yang mengikat seluruh kontraktor; mengharuskan Rekind menyelaraskan jadwal penyusunan gambar detail dengan kemajuan ISBL EPC-A. · [2] Memberikan dispensasi perpanjangan jaminan pelaksanaan secara terkendali; meminta Parent Company Guarantee dari PT Perusahaan Induk X (Persero) untuk menjamin ketersediaan pendanaan bila Rekind menghadapi kendala likuiditas.
B37: Rincian lengkap: lihat sheet 'Risk_Action_Tracker' - Executive Action Tracker Direksi/PSC.

Sheet Input_Bulanan
C2: INPUT DATA BULANAN — DIISI OLEH PIC / PROJECT CONTROL SETIAP PERIODE PELAPORAN
C3: Sel KUNING (font biru) = input manual. Sel ABU-ABU = formula otomatis, jangan diubah manual. Arahkan kursor ke label bertanda (i) untuk penjelasan parameter.
C4: Nama Perusahaan | D4: =Config!B6 -> PT Pupuk Kaltim | F4: Nama Proyek | G4: =Config!B7 -> Soda Ash
C5: Periode Pelaporan (Bulan/Tahun) | D5: 46327 | E5: Status Dokumen | F5: Final
C7: 1. EARNED VALUE MANAGEMENT (EVM) — FINANCIAL & SCHEDULE HEALTH (satuan: USD Juta, kumulatif) | D7: Skor Aktual
C8: Planned Value (PV) — kumulatif s.d. periode ini | D8: 1000
C9: Earned Value (EV) — kumulatif s.d. periode ini | D9: 1000
C10: Actual Cost (AC) — kumulatif s.d. periode ini | D10: 500
C11: Net Present Value (NPV) — USD Juta | D11: 77.6
C12: Cost Performance Index (CPI = EV/AC) | D12: =D9/D10 -> 2
C13: Cost Variance (CV = EV-AC), USD Juta | D13: =D9-D10 -> 500
C14: Schedule Performance Index (SPI = EV/PV) | D14: =D9/D8 -> 1
C15: Schedule Variance (SV = EV-PV), USD Juta | D15: =D9-D8 -> 0
C17: 2. SUPPLY READINESS INDEX | D17: Skor Aktual | E17: Bobot | F17: Tertimbang
C18: =Referensi_Threshold!A19 & " (Bobot: " & TEXT(E18, "0%") & ")" -> Salt Contract (Bobot: 25%) | D18: 0.82 | E18: =Referensi_Threshold!B19 -> 0.25 | F18: =D18*E18 -> 0.205
C19: =Referensi_Threshold!A20 & " (Bobot: " & TEXT(E19, "0%") & ")" -> Salt Inventory (Bobot: 20%) | D19: 0.8 | E19: =Referensi_Threshold!B20 -> 0.2 | F19: =D19*E19 -> 0.16
C20: =Referensi_Threshold!A21 & " (Bobot: " & TEXT(E20, "0%") & ")" -> Supplier Qualification (Bobot: 15%) | D20: 0.75 | E20: =Referensi_Threshold!B21 -> 0.15 | F20: =D20*E20 -> 0.1125
C21: =Referensi_Threshold!A22 & " (Bobot: " & TEXT(E21, "0%") & ")" -> Shipping Readiness (Bobot: 15%) | D21: 0.85 | E21: =Referensi_Threshold!B22 -> 0.15 | F21: =D21*E21 -> 0.1275
C22: =Referensi_Threshold!A23 & " (Bobot: " & TEXT(E22, "0%") & ")" -> Utility Readiness (Bobot: 15%) | D22: 0.8 | E22: =Referensi_Threshold!B23 -> 0.15 | F22: =D22*E22 -> 0.12
C23: =Referensi_Threshold!A24 & " (Bobot: " & TEXT(E23, "0%") & ")" -> Salt Readiness (Bobot: 10%) | D23: 0.8 | E23: =Referensi_Threshold!B24 -> 0.1 | F23: =D23*E23 -> 0.08
C24: SRI — Supply Readiness Index (tertimbang) | D24: =F24 -> 0.805 | E24: =SUM(E18:E23) -> 1 | F24: =SUM(F18:F23) -> 0.805
C26: 3. PROJECT EXECUTION INDEX | D26: Skor Aktual | E26: Bobot | F26: Tertimbang
C27: =Referensi_Threshold!A28 & " (Bobot: " & TEXT(E27, "0%") & ")" -> Engineering Progress (Bobot: 20%) | D27: 0.88 | E27: =Referensi_Threshold!B28 -> 0.2 | F27: =D27*E27 -> 0.176
C28: =Referensi_Threshold!A29 & " (Bobot: " & TEXT(E28, "0%") & ")" -> Procurement Progress (Bobot: 30%) | D28: 0.73 | E28: =Referensi_Threshold!B29 -> 0.3 | F28: =D28*E28 -> 0.219
C29: =Referensi_Threshold!A30 & " (Bobot: " & TEXT(E29, "0%") & ")" -> Construction Progress (Bobot: 30%) | D29: 0.82 | E29: =Referensi_Threshold!B30 -> 0.3 | F29: =D29*E29 -> 0.246
C30: =Referensi_Threshold!A31 & " (Bobot: " & TEXT(E30, "0%") & ")" -> Commissioning Preparation (Bobot: 10%) | D30: 0.42 | E30: =Referensi_Threshold!B31 -> 0.1 | F30: =D30*E30 -> 0.042
C31: =Referensi_Threshold!A32 & " (Bobot: " & TEXT(E31, "0%") & ")" -> Pencapaian Performance Test (Bobot: 10%) | D31: 0.4 | E31: =Referensi_Threshold!B32 -> 0.1 | F31: =D31*E31 -> 0.04
C32: PEI — Project Execution Index (tertimbang) | D32: =F32 -> 0.723 | E32: =SUM(E27:E31) -> 1 | F32: =SUM(F27:F31) -> 0.723
C33: Deviasi Kemajuan Fisik vs Target (S-Curve) | D33: 0.058
C35: 4. COMMERCIAL READINESS INDEX | D35: Skor Aktual | E35: Bobot | F35: Tertimbang
C36: =Referensi_Threshold!A36 & " (Bobot: " & TEXT(E36, "0%") & ")" -> Offtake Agreement (Bobot: 20%) | D36: 0.6 | E36: =Referensi_Threshold!B36 -> 0.2 | F36: =D36*E36 -> 0.12
C37: =Referensi_Threshold!A37 & " (Bobot: " & TEXT(E37, "0%") & ")" -> Marketing Strategy (Bobot: 20%) | D37: 0.6 | E37: =Referensi_Threshold!B37 -> 0.2 | F37: =D37*E37 -> 0.12
C38: =Referensi_Threshold!A38 & " (Bobot: " & TEXT(E38, "0%") & ")" -> Distribution Readiness (Bobot: 10%) | D38: 0.8 | E38: =Referensi_Threshold!B38 -> 0.1 | F38: =D38*E38 -> 0.08
C39: =Referensi_Threshold!A39 & " (Bobot: " & TEXT(E39, "0%") & ")" -> Operation Team Ready (Bobot: 20%) | D39: 0.8 | E39: =Referensi_Threshold!B39 -> 0.2 | F39: =D39*E39 -> 0.16
C40: =Referensi_Threshold!A40 & " (Bobot: " & TEXT(E40, "0%") & ")" -> Product Qualification (Bobot: 20%) | D40: 0.4 | E40: =Referensi_Threshold!B40 -> 0.2 | F40: =D40*E40 -> 0.08
C41: =Referensi_Threshold!A41 & " (Bobot: " & TEXT(E41, "0%") & ")" -> Regulatory Readiness (Bobot: 10%) | D41: 0.5 | E41: =Referensi_Threshold!B41 -> 0.1 | F41: =D41*E41 -> 0.05
C42: CRI — Commercial Readiness Index (tertimbang) | D42: =F42 -> 0.61 | E42: =SUM(E36:E41) -> 1 | F42: =SUM(F36:F41) -> 0.61
C44: 5. OVERALL RISK INDEX — sub-indeks risiko (skor 0-100) | D44: Skor Aktual | E44: Bobot
C45: Supply Risk Indeks | D45: =D24*100 -> 80.5 | E45: =Config!B21 -> 0.4
C46: Execution Risk Indeks | D46: =D32*100 -> 72.3 | E46: =Config!B22 -> 0.4
C47: Commercial Risk Indeks | D47: =D42*100 -> 61 | E47: =Config!B23 -> 0.2
C48: Overall Risk Index (tertimbang, skala 0-100) | D48: =(D45*E45)+(D46*E46)+(D47*E47) -> 73.32
C49: Overall Risk Level (5 Tingkat, formula) | D49: =IF(D48<=20,"Low",IF(D48<=44,"Low to Moderate",IF(D48<=60,"Moderate",IF(D48<=76,"Moderate to High","High")))) -> Moderate to High
C51: 6. REGISTER RISIKO AKTIF — Jumlah Risiko per 5 Tingkat
C52: High | D52: 5
C53: Moderate to High | D53: 11
C54: Moderate | D54: 18
C55: Low to Moderate | D55: 4
C56: Low | D56: 3
C57: Total Risiko Aktif | D57: =SUM(D52:D56) -> 41
C59: 7. STATUS MITIGASI & DINAMIKA PERGERAKAN RISIKO (BULAN BERJALAN)
C60: Completed Mitigations (%) | D60: 0.82 | E60: Risiko Baru (New Risk) | F60: 2
C61: Overdue Actions (%) | D61: 0.18 | E61: Risiko Eskalasi (Escalated Risk) | F61: 3
C62: On Track Mitigations (%) | D62: 0.76 | E62: Risiko Menurun (Reduced Risk) | F62: 5
C63: Need Escalation (jumlah aksi) | D63: 5 | E63: Risiko Ditutup (Closed Risk) | F63: 4
C65: 8. EARLY WARNING SYSTEM (EWS) — NILAI AKTUAL PEMANTAUAN
C66: Parameter EWS | D66: Deskripsi Target | E66: Nilai Aktual | F66: Nilai Threshold (Numerik) | G66: Buffer Waspada (Angka) | H66: Status EWS (3 Level)
C67: First Shipment | D67: Target: 1 Nov 27 (Lower is better) | E67: 46663 | F67: 46661 | G67: 30 | H67: =IF(E67<=F67, "Aman", IF(E67<=(F67+G67), "Waspada", "Bahaya")) -> Waspada
C68: Project Progress | D68: Minimal 90% (Higher is better) | E68: 0.9 | F68: 0.9 | G68: 0.05 | H68: =IF(E68>=F68, "Aman", IF(E68>=(F68-G68), "Waspada", "Bahaya")) -> Aman
C69: Offtaker Agreement | D69: Target SPI >= 1.00 (Higher is better) | E69: 0.9 | F69: 1 | G69: 0.1 | H69: =IF(E69>=F69, "Aman", IF(E69>=(F69-G69), "Waspada", "Bahaya")) -> Waspada
C72: 9. TOP RISK REGISTER — INPUT LIKELIHOOD (L) & CONSEQUENCE (C) UNTUK HEAT MAP
C73: Skala Risiko & Risk Level dihitung otomatis dari Tabel Skala Risiko Non-Linear 5x5 pada sheet Referensi_Threshold bagian 10 (bukan lagi perkalian L x C sederhana). Posisi pada Risk Profile Heat Map di sheet Dashboard mengikuti nilai L & C ini secara otomatis.
C74: Kode | D74: Deskripsi Risiko Utama | E74: Kategori | F74: L (1-5) | G74: C (1-5) | H74: Score | I74: Risk Level
C75: C1 | D75: Salt Supply Disruption (gangguan pasokan garam industri) | E75: Hulu / Supply | F75: 4 | G75: 5 | H75: =INDEX(Referensi_Threshold!$D$93:$D$117,MATCH(F75*10+G75,Referensi_Threshold!$A$93:$A$117,0)) -> 24 | I75: =INDEX(Referensi_Threshold!$E$93:$E$117,MATCH(F75*10+G75,Referensi_Threshold!$A$93:$A$117,0)) -> High
C76: C2 | D76: Commissioning Delay (keterlambatan commissioning) | E76: Eksekusi | F76: 4 | G76: 5 | H76: =INDEX(Referensi_Threshold!$D$93:$D$117,MATCH(F76*10+G76,Referensi_Threshold!$A$93:$A$117,0)) -> 24 | I76: =INDEX(Referensi_Threshold!$E$93:$E$117,MATCH(F76*10+G76,Referensi_Threshold!$A$93:$A$117,0)) -> High
C77: C3 | D77: EPC Interface Issue (isu EPC interface lintas kontraktor) | E77: Eksekusi | F77: 4 | G77: 4 | H77: =INDEX(Referensi_Threshold!$D$93:$D$117,MATCH(F77*10+G77,Referensi_Threshold!$A$93:$A$117,0)) -> 19 | I77: =INDEX(Referensi_Threshold!$E$93:$E$117,MATCH(F77*10+G77,Referensi_Threshold!$A$93:$A$117,0)) -> Moderate to High
C78: C4 | D78: Long Lead Equipment (keterlambatan peralatan utama) | E78: Pengadaan | F78: 3 | G78: 3 | H78: =INDEX(Referensi_Threshold!$D$93:$D$117,MATCH(F78*10+G78,Referensi_Threshold!$A$93:$A$117,0)) -> 13 | I78: =INDEX(Referensi_Threshold!$E$93:$E$117,MATCH(F78*10+G78,Referensi_Threshold!$A$93:$A$117,0)) -> Moderate

Sheet Risk_Action_Tracker
B2: EXECUTIVE ACTION TRACKER — DIREKSI / PROJECT STEERING COMMITTEE (PSC)
B3: Tracker Risiko & Aksi Eksekutif — diperbarui setiap periode pelaporan bulanan. Kategori Level mengikuti Risk Register aktif.
B5: No | C5: Isu Strategis / Peristiwa Risiko Kritis | D5: Kategori & Level Risiko | E5: Keputusan & Rencana Tindakan Diperlukan | F5: PIC (Unit Penanggung Jawab) | G5: Perkiraan Dampak Finansial & Kelayakan NPV | H5: Prioritas Dashboard (1, 2, 3...) | Z5: Helper Priority Score
B6: 1 | C6: Ketergantungan Antarmuka (Interface) Lintas EPC-A, B, C, D | D6: Eksekusi — High | E6: Mengesahkan pembentukan tim Interface Coordinator dan menerapkan Interface Management Plan (IMP) yang mengikat seluruh kontraktor; mengharuskan Rekind menyelaraskan jadwal penyusunan gambar detail dengan kemajuan ISBL EPC-A. | F6: VP Proyek Proyek & SVP Pengembangan Portofolio | G6: Mencegah kegagalan penyelesaian proyek bersamaan, mengamankan target COD Maret 2028, melindungi NPV sebesar USD 77,60 Juta. | H6: 1 | Z6: =IF(D6="","", IF(ISNUMBER(SEARCH("Moderate to High", D6)), 40, IF(ISNUMBER(SEARCH("High", D6)), 50, IF(ISNUMBER(SEARCH("Low to Moderate", D6)), 20, IF(ISNUMBER(SEARCH("Moderate", D6)), 30, 10)))) + (1/ROW())) -> 50.166667
B7: 2 | C7: Keterbatasan Kapasitas Keuangan Rekind (EPC-B) | D7: Finansial — Moderate to High | E7: Memberikan dispensasi perpanjangan jaminan pelaksanaan secara terkendali; meminta Parent Company Guarantee dari PT Perusahaan Induk X (Persero) untuk menjamin ketersediaan pendanaan bila Rekind menghadapi kendala likuiditas. | F7: Direktur Utama Perusahaan & SVP Keuangan | G7: Melindungi penyelesaian gardu kelistrikan dan fasilitas tie-in, menghindari denda klaim tambahan dari EPC-A. | H7: 2 | Z7: =IF(D7="","", IF(ISNUMBER(SEARCH("Moderate to High", D7)), 40, IF(ISNUMBER(SEARCH("High", D7)), 50, IF(ISNUMBER(SEARCH("Low to Moderate", D7)), 20, IF(ISNUMBER(SEARCH("Moderate", D7)), 30, 10)))) + (1/ROW())) -> 40.142857
B8: 3 | C8: Kelangkaan & Hambatan Perizinan Impor Garam Industri | D8: Hulu / Supply — Moderate to High | E8: Lobi aktif dan koordinasi dengan Kementerian Perindustrian serta Kementerian Kelautan dan Perikanan guna mengamankan alokasi kuota impor tahunan setahun sebelum operasional dimulai, merujuk Perpres No.17/2025. | F8: Direktur Utama Perusahaan & SVP Pengembangan Portofolio | G8: Menghindari penghentian operasional akibat kekosongan bahan baku; menghemat potensi kerugian EBITDA Rp 137 Miliar/kuartal. | H8: 3 | Z8: =IF(D8="","", IF(ISNUMBER(SEARCH("Moderate to High", D8)), 40, IF(ISNUMBER(SEARCH("High", D8)), 50, IF(ISNUMBER(SEARCH("Low to Moderate", D8)), 20, IF(ISNUMBER(SEARCH("Moderate", D8)), 30, 10)))) + (1/ROW())) -> 40.125
B9: 4 | C9: Fluktuasi Nilai Tukar Valas Terhadap Sisa Pembayaran Kontrak EPC-A | D9: Keuangan — Moderate | E9: Menginstruksikan Kompartemen Keuangan mengimplementasikan strategi hedging valas (forward/opsi) bekerja sama dengan bank BUMN nasional untuk mengunci porsi sisa pembayaran dalam USD. | F9: Direktur Keuangan Perusahaan | G9: Mengeliminasi risiko pembengkakan biaya investasi riil akibat depresiasi rupiah; mengamankan ambang batas investasi USD 297,67 Juta. | H9: 4 | Z9: =IF(D9="","", IF(ISNUMBER(SEARCH("Moderate to High", D9)), 40, IF(ISNUMBER(SEARCH("High", D9)), 50, IF(ISNUMBER(SEARCH("Low to Moderate", D9)), 20, IF(ISNUMBER(SEARCH("Moderate", D9)), 30, 10)))) + (1/ROW())) -> 30.111111
B10: 5 | C10: Hambatan Penerbitan PBG & SLF di Lahan Tursina Barat | D10: Regulasi — Moderate | E10: Membentuk tim percepatan perizinan internal untuk koordinasi harian dengan DLH Kota X dan Dinas PUPR Provinsi Provinsi X guna mempercepat adendum dokumen lingkungan di lahan sengketa. | F10: VP Hukum & Humas Perusahaan | G10: Mencegah keterlambatan masa efektif konstruksi fisik; menghemat opportunity cost of capital senilai Rp 500 Juta/bulan. | H10: 5 | Z10: =IF(D10="","", IF(ISNUMBER(SEARCH("Moderate to High", D10)), 40, IF(ISNUMBER(SEARCH("High", D10)), 50, IF(ISNUMBER(SEARCH("Low to Moderate", D10)), 20, IF(ISNUMBER(SEARCH("Moderate", D10)), 30, 10)))) + (1/ROW())) -> 30.1
Z11: =IF(D11="","", IF(ISNUMBER(SEARCH("Moderate to High", D11)), 40, IF(ISNUMBER(SEARCH("High", D11)), 50, IF(ISNUMBER(SEARCH("Low to Moderate", D11)), 20, IF(ISNUMBER(SEARCH("Moderate", D11)), 30, 10)))) + (1/ROW()))
B12: Sumber tata kelola: kerangka Gate Review & FID industri; Weighted Project Top Risk (Financial Materiality 40%, Strategic Impact 30%, Life Cycle Phase 15%, Financial Health Impact 10%, Baseline Risk Complexity 5%). Level risiko mengikuti klasifikasi 5-tingkat Pedoman Manajemen Risiko Perusahaan: Low / Low to Moderate / Moderate / Moderate to High / High. | Z12: =IF(D12="","", IF(ISNUMBER(SEARCH("Moderate to High", D12)), 40, IF(ISNUMBER(SEARCH("High", D12)), 50, IF(ISNUMBER(SEARCH("Low to Moderate", D12)), 20, IF(ISNUMBER(SEARCH("Moderate", D12)), 30, 10)))) + (1/ROW()))
Z13: =IF(D13="","", IF(ISNUMBER(SEARCH("Moderate to High", D13)), 40, IF(ISNUMBER(SEARCH("High", D13)), 50, IF(ISNUMBER(SEARCH("Low to Moderate", D13)), 20, IF(ISNUMBER(SEARCH("Moderate", D13)), 30, 10)))) + (1/ROW()))
Z14: =IF(D14="","", IF(ISNUMBER(SEARCH("Moderate to High", D14)), 40, IF(ISNUMBER(SEARCH("High", D14)), 50, IF(ISNUMBER(SEARCH("Low to Moderate", D14)), 20, IF(ISNUMBER(SEARCH("Moderate", D14)), 30, 10)))) + (1/ROW()))
Z15: =IF(D15="","", IF(ISNUMBER(SEARCH("Moderate to High", D15)), 40, IF(ISNUMBER(SEARCH("High", D15)), 50, IF(ISNUMBER(SEARCH("Low to Moderate", D15)), 20, IF(ISNUMBER(SEARCH("Moderate", D15)), 30, 10)))) + (1/ROW()))
B16: DINAMIKA PERGERAKAN RISIKO (BULAN BERJALAN)
B17: Risiko Baru (New Risk) | C17: =Input_Bulanan!F60 -> 2 | D17: Perubahan tarif pajak masukan impor garam industri; risiko sengketa lahan tambahan di area laydown.
B18: Risiko Eskalasi (Escalated Risk) | C18: =Input_Bulanan!F61 -> 3 | D18: Peningkatan level risiko keterlambatan Rekind akibat kendala arus kas internal.
B19: Risiko Menurun (Reduced Risk) | C19: =Input_Bulanan!F62 -> 5 | D19: Penurunan risiko dampak sosial setelah disepakatinya kuota tenaga kerja lokal.
B20: Risiko Ditutup (Closed Risk) | C20: =Input_Bulanan!F63 -> 4 | D20: Penutupan risiko kelayakan AMDAL seiring diterbitkannya izin adendum lingkungan DLH Bontang.
B22: TOP RISK REGISTER - DETAIL LIKELIHOOD x CONSEQUENCE
B23: Kode | C23: Deskripsi Risiko | D23: Kategori | E23: L | F23: C | G23: Score / Level
B24: =Input_Bulanan!C75 -> C1 | C24: =Input_Bulanan!D75 -> Salt Supply Disruption (gangguan pasokan garam industri) | D24: =Input_Bulanan!E75 -> Hulu / Supply | E24: =Input_Bulanan!F75 -> 4 | F24: =Input_Bulanan!G75 -> 5 | G24: =Input_Bulanan!H75 & " | " & Input_Bulanan!I75 -> 24 | High
B25: =Input_Bulanan!C76 -> C2 | C25: =Input_Bulanan!D76 -> Commissioning Delay (keterlambatan commissioning) | D25: =Input_Bulanan!E76 -> Eksekusi | E25: =Input_Bulanan!F76 -> 4 | F25: =Input_Bulanan!G76 -> 5 | G25: =Input_Bulanan!H76 & " | " & Input_Bulanan!I76 -> 24 | High
B26: =Input_Bulanan!C77 -> C3 | C26: =Input_Bulanan!D77 -> EPC Interface Issue (isu EPC interface lintas kontraktor) | D26: =Input_Bulanan!E77 -> Eksekusi | E26: =Input_Bulanan!F77 -> 4 | F26: =Input_Bulanan!G77 -> 4 | G26: =Input_Bulanan!H77 & " | " & Input_Bulanan!I77 -> 19 | Moderate to High
B27: =Input_Bulanan!C78 -> C4 | C27: =Input_Bulanan!D78 -> Long Lead Equipment (keterlambatan peralatan utama) | D27: =Input_Bulanan!E78 -> Pengadaan | E27: =Input_Bulanan!F78 -> 3 | F27: =Input_Bulanan!G78 -> 3 | G27: =Input_Bulanan!H78 & " | " & Input_Bulanan!I78 -> 13 | Moderate
